passport_cropper/__init__.py
passport_cropper/cropper.py
passport_cropper/utils.py
passport_cropper-0.1.1.dist-info/licenses/LICENSE
passport_cropper-0.1.1.dist-info/METADATA
passport_cropper-0.1.1.dist-info/WHEEL
passport_cropper-0.1.1.dist-info/top_level.txt
passport_cropper-0.1.1.dist-info/RECORD
