Metadata-Version: 2.4
Name: passport-cropper
Version: 0.1.1
Summary: Auto-crop passport photos from scanned documents using face detection.
Home-page: https://github.com/abhaybraja/passport-cropper
Author: Abhay Braja
Author-email: Abhay Braja <abhaybraja@gmail.com>
License: MIT
Project-URL: Homepage, https://github.com/abhaybraja/passport-cropper
Project-URL: Repository, https://github.com/abhaybraja/passport-cropper
Requires-Python: >=3.7
License-File: LICENSE
Requires-Dist: opencv-python
Requires-Dist: numpy
Dynamic: author
Dynamic: home-page
Dynamic: license-file
Dynamic: requires-python
